scrapyrt/VERSION
scrapyrt/__init__.py
scrapyrt/cmdline.py
scrapyrt/core.py
scrapyrt/decorators.py
scrapyrt/exceptions.py
scrapyrt/log.py
scrapyrt/resources.py
scrapyrt/utils.py
scrapyrt/conf/__init__.py
scrapyrt/conf/default_settings.py
scrapyrt/conf/spider_settings.py
tests/__init__.py
tests/servers.py
tests/spiders.py
tests/test_cmdline.py
tests/test_crawl_manager.py
tests/test_crawler.py
tests/test_crawler_process.py
tests/test_decorators.py
tests/test_log_observer.py
tests/test_resource_crawl.py
tests/test_resource_realtimeapi.py
tests/test_resource_root.py
tests/test_resource_serviceresource.py
tests/test_utils.py
tests/utils.py
tests/test_settings/__init__.py
tests/test_settings/default_settings.py
tests/test_settings/settings.py
scrapyrt_with_params-0.13.2.dist-info/LICENSE
scrapyrt_with_params-0.13.2.dist-info/METADATA
scrapyrt_with_params-0.13.2.dist-info/WHEEL
scrapyrt_with_params-0.13.2.dist-info/entry_points.txt
scrapyrt_with_params-0.13.2.dist-info/top_level.txt
scrapyrt_with_params-0.13.2.dist-info/RECORD
