Metadata-Version: 2.1
Name: scrapyrt-with-params
Version: 0.13.2
Summary: Put Scrapy spiders behind an HTTP API
Home-page: https://github.com/manueltg89/scrapyrt-with-params
Author: Manuel Trinidad Garcia
Author-email: manuel.trinidad.garcia@hotmail.com
Maintainer: Scrapinghub
Maintainer-email: manuel.trinidad.garcia@hotmail.com
License: BSD
Project-URL: Documentation, https://scrapyrt.readthedocs.io/en/latest/index.html
Project-URL: Source, https://github.com/scrapinghub/scrapyrt
Project-URL: Tracker, https://github.com/scrapinghub/scrapyrt/issues
Platform: UNKNOWN
Classifier: Programming Language :: Python
Classifier: Programming Language :: Python :: 3
Classifier: Programming Language :: Python :: 3.6
Classifier: Programming Language :: Python :: 3.7
Classifier: Programming Language :: Python :: 3.8
Classifier: Programming Language :: Python :: 3.9
Classifier: Programming Language :: Python :: 3.10
Classifier: Operating System :: OS Independent
Classifier: Environment :: Console
Classifier: Environment :: No Input/Output (Daemon)
Classifier: Topic :: Internet :: WWW/HTTP
Classifier: License :: OSI Approved :: BSD License
Requires-Python: >=3.6
License-File: LICENSE
Requires-Dist: Scrapy (>=1.0.0)
